MANIFEST.in
README.md
pyproject.toml
setup.py
src/maskerade.rides3_secure_bucket.egg-info/PKG-INFO
src/maskerade.rides3_secure_bucket.egg-info/SOURCES.txt
src/maskerade.rides3_secure_bucket.egg-info/dependency_links.txt
src/maskerade.rides3_secure_bucket.egg-info/requires.txt
src/maskerade.rides3_secure_bucket.egg-info/top_level.txt
src/maskerade/rides3_secure_bucket/__init__.py
src/maskerade/rides3_secure_bucket/py.typed
src/maskerade/rides3_secure_bucket/_jsii/__init__.py
src/maskerade/rides3_secure_bucket/_jsii/rides3-secure-bucket@0.3.0.jsii.tgz