Metadata-Version: 2.1
Name: maskerade.rides3-secure-bucket
Version: 0.3.0
Summary: rides3-secure-bucket
Home-page: https://github.com/maskerade/cdk-jsii-demo01.git
Author: Stefan De Figueiredo
License: ISC
Project-URL: Source, https://github.com/maskerade/cdk-jsii-demo01.git
Platform: UNKNOWN
Classifier: Intended Audience :: Developers
Classifier: Operating System :: OS Independent
Classifier: Programming Language :: JavaScript
Classifier: Programming Language :: Python :: 3 :: Only
Classifier: Programming Language :: Python :: 3.6
Classifier: Programming Language :: Python :: 3.7
Classifier: Programming Language :: Python :: 3.8
Classifier: Typing :: Typed
Classifier: License :: OSI Approved
Requires-Python: >=3.6
